{
  "main": {
    "id": "39f64a330c6f1138",
    "type": "split",
    "children": [
      {
        "id": "e1864dbe492be079",
        "type": "tabs",
        "children": [
          {
            "id": "993cd22a657b2210",
            "type": "leaf",
            "state": {
              "type": "markdown",
              "state": {
                "file": "WEB-Lamp-Arch.md",
                "mode": "source",
                "source": false
              }
            }
          },
          {
            "id": "63347a7deb32da0d",
            "type": "leaf",
            "state": {
              "type": "markdown",
              "state": {
                "file": "WEB-Lamp-Arch.md",
                "mode": "source",
                "source": false
              }
            }
          }
        ],
        "currentTab": 1
      }
    ],
    "direction": "vertical"
  },
  "left": {
    "id": "f4761f93f7d028e5",
    "type": "split",
    "children": [
      {
        "id": "2444ac4a0b84638f",
        "type": "tabs",
        "children": [
          {
            "id": "2fc54a231507d63c",
            "type": "leaf",
            "state": {
              "type": "file-explorer",
              "state": {
                "sortOrder": "alphabetical"
              }
            }
          },
          {
            "id": "e2f1473be83a3039",
            "type": "leaf",
            "state": {
              "type": "search",
              "state": {
                "query": "",
                "matchingCase": false,
                "explainSearch": false,
                "collapseAll": false,
                "extraContext": false,
                "sortOrder": "alphabetical"
              }
            }
          },
          {
            "id": "f10a1ff1f894dec5",
            "type": "leaf",
            "state": {
              "type": "bookmarks",
              "state": {}
            }
          }
        ]
      }
    ],
    "direction": "horizontal",
    "width": 200
  },
  "right": {
    "id": "0655edfaf96dcf8f",
    "type": "split",
    "children": [
      {
        "id": "19a7b5d5b93bae2a",
        "type": "tabs",
        "children": [
          {
            "id": "2fdc88fff25de7fb",
            "type": "leaf",
            "state": {
              "type": "backlink",
              "state": {
                "file": "WEB-Lamp-Arch.md",
                "collapseAll": true,
                "extraContext": false,
                "sortOrder": "alphabetical",
                "showSearch": false,
                "searchQuery": "",
                "backlinkCollapsed": false,
                "unlinkedCollapsed": true
              }
            }
          },
          {
            "id": "f0fe9b63a9d4788b",
            "type": "leaf",
            "state": {
              "type": "outgoing-link",
              "state": {
                "file": "WEB-Lamp-Arch.md",
                "linksCollapsed": false,
                "unlinkedCollapsed": true
              }
            }
          },
          {
            "id": "689cecb11d0e5df4",
            "type": "leaf",
            "state": {
              "type": "tag",
              "state": {
                "sortOrder": "frequency",
                "useHierarchy": true
              }
            }
          },
          {
            "id": "35f08b8036524f7f",
            "type": "leaf",
            "state": {
              "type": "outline",
              "state": {
                "file": "WEB-Lamp-Arch.md"
              }
            }
          },
          {
            "id": "b6c80088ecd0d68e",
            "type": "leaf",
            "state": {
              "type": "all-properties",
              "state": {
                "sortOrder": "frequency",
                "showSearch": false,
                "searchQuery": ""
              }
            }
          }
        ],
        "currentTab": 3
      }
    ],
    "direction": "horizontal",
    "width": 300,
    "collapsed": true
  },
  "left-ribbon": {
    "hiddenItems": {
      "switcher:Open quick switcher": false,
      "graph:Open graph view": false,
      "canvas:Create new canvas": false,
      "templates:Insert template": false,
      "command-palette:Open command palette": false
    }
  },
  "active": "63347a7deb32da0d",
  "lastOpenFiles": [
    "extract image metadata.md",
    "BASH-findMove.md",
    "WEB-Lamp-Arch.md",
    "WEB-laravelnstallation.md",
    "WEB-LAMP.md",
    "VIM-VimKey.md",
    "TOOLS-tlp.md",
    "mazil.md",
    "BOOT-grubConfigF38.md",
    "FLATPAK- blurryFonts.md",
    "TOOL-ifuse.md",
    "LinuxDailyApps.md",
    "WEB-LAMP-ArchLinux.md",
    "nmcliPwd.md",
    "BASH-pacmanCS.md",
    "pdfManupliate.md",
    "spotifyAdblock.md",
    "BOOT-grubConfigManjaro.md",
    "TOOL-soffice.md",
    "WEB-xamppInstallLinux.md",
    "BASH-changeFileFolderPermisson.md",
    "TOOL-wget.md",
    "WEB-css_mini_course.md",
    "BASH-FileFolderManipulation.md",
    "SQLbasicDB.md",
    "Untitled.canvas",
    "Hello.md",
    "Templates/blogMenu.txt",
    "Templates",
    "Templates/blogMenu"
  ]
}
